chatty_goose/__init__.py
chatty_goose/logger.py
chatty_goose/settings.py
chatty_goose/types.py
chatty_goose/util.py
chatty_goose/agents/__init__.py
chatty_goose/agents/chat.py
chatty_goose/cqr/__init__.py
chatty_goose/cqr/cqr.py
chatty_goose/cqr/hqe.py
chatty_goose/cqr/ntr.py
chatty_goose/pipeline/__init__.py
chatty_goose/pipeline/retrieval_pipeline.py
chatty_goose-0.2.0.dist-info/LICENSE
chatty_goose-0.2.0.dist-info/METADATA
chatty_goose-0.2.0.dist-info/WHEEL
chatty_goose-0.2.0.dist-info/top_level.txt
chatty_goose-0.2.0.dist-info/RECORD
