Metadata-Version: 2.1
Name: chatty-goose
Version: 0.2.0
Summary: A conversational passage retrieval toolkit
Home-page: https://github.com/castorini/chatty-goose
Author: Anserini Gaggle
Author-email: anserini.gaggle@gmail.com
License: UNKNOWN
Platform: UNKNOWN
Classifier: Programming Language :: Python :: 3
Classifier: License :: OSI Approved :: Apache Software License
Classifier: Operating System :: OS Independent
Requires-Python: >=3.7
Requires-Dist: coloredlogs
Requires-Dist: parlai (==1.1.0)
Requires-Dist: pydantic (>=1.5)
Requires-Dist: pygaggle (==0.0.3.1)
Requires-Dist: spacy (<=2.3.5,>=2.2.4)
